awstaga/__init__.py
awstaga/config.py
awstaga/logger.py
awstaga/models/__init__.py
awstaga/models/resource.py
awstaga/models/tag.py
awstaga/models/tagset.py
awstaga-2.0.0.dist-info/LICENSE
awstaga-2.0.0.dist-info/METADATA
awstaga-2.0.0.dist-info/WHEEL
awstaga-2.0.0.dist-info/entry_points.txt
awstaga-2.0.0.dist-info/RECORD
