Metadata-Version: 2.3
Name: awstaga
Version: 2.0.0
Summary: Python CLI for tagging AWS resources based on a YAML configuration
License: Apache-2.0
Keywords: awstaga,aws,tag,tagging
Author: Cliffano Subagio
Author-email: cliffano@gmail.com
Requires-Python: >=3.10,<4.0
Classifier: License :: OSI Approved :: Apache Software License
Classifier: Operating System :: OS Independent
Classifier: Programming Language :: Python :: 3
Classifier: Programming Language :: Python :: 3.10
Classifier: Programming Language :: Python :: 3.11
Classifier: Programming Language :: Python :: 3.12
Classifier: Programming Language :: Python :: 3.13
Requires-Dist: PyYAML (==6.0.2)
Requires-Dist: boto3 (==1.38.27)
Requires-Dist: click (==8.2.1)
Requires-Dist: conflog (==2.0.1)
Requires-Dist: pyyaml-include (>=1.3.2,<2.0.0)
Project-URL: Documentation, https://github.com/cliffano/awstaga
Project-URL: Homepage, https://github.com/cliffano/awstaga
Project-URL: Repository, https://github.com/cliffano/awstaga
